CHANGES.txt
MANIFEST.in
README.rst
setup.cfg
setup.py
hapis/__init__.py
hapis/settings.py
hapis.egg-info/PKG-INFO
hapis.egg-info/SOURCES.txt
hapis.egg-info/dependency_links.txt
hapis.egg-info/requires.txt
hapis.egg-info/top_level.txt
hapis.egg-info/zip-safe
hapis/tests/__init__.py