Metadata-Version: 1.1
Name: hapis
Version: 0.1a2
Summary: A collection of packages that help with creating of plugins for Pyramid web framework
Home-page: https://github.com/grisumbras/hapis
Author: Dmitry Arkhipov
Author-email: grisumbras@gmail.com
License: MIT License
Keywords: web pyramid configuration plugins
Platform: UNKNOWN
Classifier: Development Status :: 3 - Alpha
Classifier: Programming Language :: Python
Classifier: Framework :: Pyramid
Classifier: Intended Audience :: Developers
Classifier: License :: OSI Approved :: MIT License
Classifier: Topic :: Internet :: WWW/HTTP :: WSGI :: Application
Classifier: Topic :: Software Development :: Libraries :: Python Modules
